Unit_c/len.py
Unit_c/len_c.py
Unit_c/speed.py
Unit_c/speed_c.py
Unit_c/tem.py
Unit_c/tem_c.py
leeUnit_c-0.0.2.dist-info/LICENSE
leeUnit_c-0.0.2.dist-info/METADATA
leeUnit_c-0.0.2.dist-info/WHEEL
leeUnit_c-0.0.2.dist-info/top_level.txt
leeUnit_c-0.0.2.dist-info/RECORD
