Metadata-Version: 2.1
Name: leeUnit_c
Version: 0.0.2
Summary: Converts many different units
Home-page: https://github.com/Lsh0402/leeUnit_c.git
Download-URL: https://github.com/Lsh0402/leeUnit_c.git
Author: leeseunghun
Classifier: Programming Language :: Python :: 3
License-File: LICENSE
